cvpoc/__init__.py
cvpoc/cli.py
cvpoc/console.py
cvpoc/cv.py
cvpoc/poc.py
cvpoc/test.py
cvpoc/api/__init__.py
cvpoc/cv_pocs/__init__.py
cvpoc/cv_pocs/thinkphp_rce2.py
cvpoc/easy_pocs/__init__.py
cvpoc/easy_pocs/thinkphp2.py
cvpoc/easypoc/__init__.py
cvpoc/easypoc/data.py
cvpoc/easypoc/loader.py
cvpoc/easypoc/requests.py
cvpoc/easypoc/threads.py
cvpoc/lib/__init__.py
cvpoc/lib/controller/__init__.py
cvpoc/lib/controller/controller.py
cvpoc/lib/core/__init__.py
cvpoc/lib/core/clear.py
cvpoc/lib/core/common.py
cvpoc/lib/core/convert.py
cvpoc/lib/core/data.py
cvpoc/lib/core/datatype.py
cvpoc/lib/core/decorators.py
cvpoc/lib/core/enums.py
cvpoc/lib/core/exception.py
cvpoc/lib/core/interpreter.py
cvpoc/lib/core/interpreter_option.py
cvpoc/lib/core/log.py
cvpoc/lib/core/option.py
cvpoc/lib/core/optiondict.py
cvpoc/lib/core/plugin.py
cvpoc/lib/core/poc.py
cvpoc/lib/core/readlineng.py
cvpoc/lib/core/register.py
cvpoc/lib/core/revision.py
cvpoc/lib/core/settings.py
cvpoc/lib/core/shell.py
cvpoc/lib/core/statistics_comparison.py
cvpoc/lib/core/threads.py
cvpoc/lib/helper/__init__.py
cvpoc/lib/helper/archieve/__init__.py
cvpoc/lib/helper/archieve/jar.py
cvpoc/lib/helper/archieve/memoryzip.py
cvpoc/lib/helper/archieve/war.py
cvpoc/lib/helper/archieve/zip.py
cvpoc/lib/helper/java/__init__.py
cvpoc/lib/helper/java/serialization.py
cvpoc/lib/parse/__init__.py
cvpoc/lib/parse/cmd.py
cvpoc/lib/parse/configfile.py
cvpoc/lib/parse/url.py
cvpoc/lib/request/__init__.py
cvpoc/lib/request/patch/__init__.py
cvpoc/lib/request/patch/add_httpraw.py
cvpoc/lib/request/patch/hook_request.py
cvpoc/lib/request/patch/hook_request_redirect.py
cvpoc/lib/request/patch/remove_ssl_verify.py
cvpoc/lib/request/patch/remove_warnings.py
cvpoc/lib/utils/__init__.py
cvpoc/modules/__init__.py
cvpoc/modules/httpserver/__init__.py
cvpoc/modules/listener/__init__.py
cvpoc/modules/listener/bind_tcp.py
cvpoc/modules/listener/reverse_tcp.py
cvpoc/modules/spider/__init__.py
cvpoc/pocs/__init__.py
cvpoc-1.0.1.dist-info/METADATA
cvpoc-1.0.1.dist-info/WHEEL
cvpoc-1.0.1.dist-info/entry_points.txt
cvpoc-1.0.1.dist-info/top_level.txt
cvpoc-1.0.1.dist-info/RECORD
